basilo/__init__.py
basilo-0.0.0.dist-info/WHEEL
basilo-0.0.0.dist-info/METADATA
basilo-0.0.0.dist-info/RECORD
