Metadata-Version: 2.1
Name: basilo
Version: 0.0.0
Summary: An opinionated data manipulation Python package.
Author: chris pryer
Author-email: christophpryer@gmail.com
Requires-Python: >=3.10,<4.0
Classifier: Programming Language :: Python :: 3
Classifier: Programming Language :: Python :: 3.10
